PPM_Common/ElasticManager.py
PPM_Common/MongoManager.py
PPM_Common/__init__.py
PPM_Common/classconfig/DatabaseConfiguration.py
PPM_Common/classconfig/ElasticConfiguration.py
PPM_Common/classconfig/MongoConfiguration.py
PPM_Common/classconfig/__init__.py
PPM_Common/databaseconnexion/DatabaseConfigurationLoader.py
PPM_Common/databaseconnexion/ElasticConnexion.py
PPM_Common/databaseconnexion/MongoConnexion.py
PPM_Common/databaseconnexion/__init__.py
PPM_Common/exception/ParseConfigurationException.py
PPM_Common/exception/__init__.py
PPM_Common/json/JSONConstant.py
PPM_Common/json/JSONUtils.py
PPM_Common/json/__init__.py
PPM_Common-0.0.1.dist-info/DESCRIPTION.rst
PPM_Common-0.0.1.dist-info/METADATA
PPM_Common-0.0.1.dist-info/RECORD
PPM_Common-0.0.1.dist-info/WHEEL
PPM_Common-0.0.1.dist-info/metadata.json
PPM_Common-0.0.1.dist-info/top_level.txt
test/classconfig/__init__.py
test/classconfig/test_databaseConfigurationLoader.py
test/conf/__init__.py
test/mongodb/__init__.py
test/mongodb/test_MongoManager.py
test/mongodb/test_databaseConnexion.py
