Metadata-Version: 2.0
Name: PPM-Common
Version: 0.0.1
Summary: Tools for connection to mongodDB et Elasticsearch
Home-page: https://github.com/Histofig/PPM_Common
Author: Fanny
Author-email: fanny.esposito@histofig.com
License: UNKNOWN
Platform: UNKNOWN
Classifier: Programming Language :: Python
Classifier: Development Status :: 1 - Planning
Classifier: Environment :: Web Environment
Classifier: Intended Audience :: Developers
Classifier: License :: OSI Approved :: Apache Software License
Classifier: Natural Language :: French
Classifier: Operating System :: POSIX :: Linux
Classifier: Programming Language :: Python :: 3.3
Classifier: Topic :: Software Development :: Libraries :: Python Modules
Requires-Dist: bson
Requires-Dist: pymongo
Requires-Dist: elasticsearch (<7.0.0,>=6.0.0)
